FasterPip/FasterPip.py
FasterPip/__init__.py
FasterPip/en_us/__init__.py
FasterPip/en_us/download.py
FasterPip/en_us/file_install.py
FasterPip/en_us/uninstall.py
FasterPip/en_us/upgrade.py
FasterPip/en_us/upgrade_all.py
FasterPip/en_us/web_install.py
FasterPip/zh_cn/__init__.py
FasterPip/zh_cn/download.py
FasterPip/zh_cn/file_install.py
FasterPip/zh_cn/uninstall.py
FasterPip/zh_cn/upgrade.py
FasterPip/zh_cn/web_install.py
FasterPip-2.7.dist-info/License
FasterPip-2.7.dist-info/METADATA
FasterPip-2.7.dist-info/WHEEL
FasterPip-2.7.dist-info/top_level.txt
FasterPip-2.7.dist-info/RECORD
