Metadata-Version: 2.1
Name: FasterPip
Version: 2.7
Summary: Faster pip for Python users can be used to install Python modules.
Home-page: https://mstouk57g.github.io/FasterPip/
Author: mstouk57g
Author-email: mstouk57g@yeah.net
License: UNKNOWN
Project-URL: Documentation, https://github.com/mstouk57g/FasterPip/blob/main/README.md
Project-URL: Source, https://github.com/mstouk57g/FasterPip
Project-URL: Changelog, https://github.com/mstouk57g/FasterPip/releases
Platform: UNKNOWN
Classifier: Programming Language :: Python :: 3
Classifier: Programming Language :: Python :: 3 :: Only
Classifier: Programming Language :: Python :: 3.9
Classifier: Programming Language :: Python :: Implementation :: CPython
Classifier: License :: OSI Approved :: MIT License
Classifier: Operating System :: OS Independent
Classifier: Topic :: Software Development :: Build Tools
Requires-Python: >=3.9.0
